jl_realtime_py/__init__.py
jl_realtime_py/channel.py
jl_realtime_py/connection.py
jl_realtime_py/exceptions.py
jl_realtime_py/message.py
jl_realtime_py/transformers.py
jl_realtime_py-0.2.1.dist-info/LICENSE
jl_realtime_py-0.2.1.dist-info/WHEEL
jl_realtime_py-0.2.1.dist-info/METADATA
jl_realtime_py-0.2.1.dist-info/RECORD
