Metadata-Version: 2.1
Name: jl-realtime-py
Version: 0.2.1
Summary: 
Author: None
Requires-Python: >=3.7,<4.0
Classifier: Programming Language :: Python :: 3
Classifier: Programming Language :: Python :: 3.7
Classifier: Programming Language :: Python :: 3.8
Classifier: Programming Language :: Python :: 3.9
Requires-Dist: dataclasses (>=0.6,<0.7)
Requires-Dist: python-dateutil (>=2.8.1,<3.0.0)
Requires-Dist: websockets (>=8.1,<9.0)
